asynctaskpool/__init__.py
asynctaskpool/task_failed_exception.py
asynctaskpool/taskpool.py
asynctaskpool/taskpool_task.py
asynctaskpool-0.2.1.dist-info/METADATA
asynctaskpool-0.2.1.dist-info/WHEEL
asynctaskpool-0.2.1.dist-info/RECORD
