Metadata-Version: 2.1
Name: asynctaskpool
Version: 0.2.1
Summary: Provides a task pool for asynchronous tasks to be executed only once.
Home-page: https://codeberg.org/QCanvas/AsyncTaskPool
Keywords: async,taskpool
Author: QCanvas
Author-email: qcanvas@noreply.codeberg.org
Requires-Python: >=3.10,<4.0
Classifier: Framework :: AsyncIO
Classifier: Programming Language :: Python :: 3
Classifier: Programming Language :: Python :: 3.10
Classifier: Programming Language :: Python :: 3.11
Classifier: Programming Language :: Python :: 3.12
Project-URL: Repository, https://codeberg.org/QCanvas/AsyncTaskPool
